abmap/__init__.py
abmap/__main__.py
abmap/abmap_augment.py
abmap/base_config.py
abmap/dataloader.py
abmap/libraseq_preprocess.py
abmap/model.py
abmap/mutate.py
abmap/plm_embed.py
abmap/sabdab_preprocess.py
abmap/utils.py
abmap/version.py
abmap/commands/__init__.py
abmap/commands/augment.py
abmap/commands/embed.py
abmap/commands/train.py
analysis/__init__.py
analysis/briney_analysis.py
analysis/covabdab_analyze.py
analysis/desautels_analyze.py
analysis/strucpred_analysis.py
analysis/thera_analysis.py
abmap-0.1.4.dist-info/LICENSE.txt
abmap-0.1.4.dist-info/METADATA
abmap-0.1.4.dist-info/WHEEL
abmap-0.1.4.dist-info/entry_points.txt
abmap-0.1.4.dist-info/top_level.txt
abmap-0.1.4.dist-info/RECORD
