Metadata-Version: 2.1
Name: abmap
Version: 0.1.4
Summary: AbMAP: Antibody Mutagenesis Augmented Processing
Author: Chiho Im, Taylor Sorenson, Abhinav Gupta, Rohit Singh
Author-email: Chiho Im <chihoim@mit.edu>, Rohit Singh <rohitsingh@gmail.com>
Classifier: Programming Language :: Python :: 3
Classifier: License :: OSI Approved :: MIT License
Classifier: Operating System :: OS Independent
Requires-Python: >=3.7
License-File: LICENSE.txt
Requires-Dist: numpy
Requires-Dist: scipy
Requires-Dist: pandas
Requires-Dist: torch (>=1.11)
Requires-Dist: biopython
Requires-Dist: matplotlib
Requires-Dist: seaborn
Requires-Dist: tqdm
Requires-Dist: scikit-learn
Requires-Dist: h5py
Requires-Dist: transformers
Requires-Dist: positional-encodings
Requires-Dist: dscript
